kakakucom/__init__.py
kakakucom/main.py
kakakucom/model/__init__.py
kakakucom/model/item.py
kakakucom/site/__init__.py
kakakucom/site/ranking.py
kakakucom-0.2.0.dist-info/METADATA
kakakucom-0.2.0.dist-info/WHEEL
kakakucom-0.2.0.dist-info/entry_points.txt
kakakucom-0.2.0.dist-info/top_level.txt
kakakucom-0.2.0.dist-info/RECORD
